rgg_save_tool/__init__.py
rgg_save_tool/rgg_save_tool.py
rgg_save_tool-0.1.1.dist-info/LICENSE
rgg_save_tool-0.1.1.dist-info/METADATA
rgg_save_tool-0.1.1.dist-info/WHEEL
rgg_save_tool-0.1.1.dist-info/entry_points.txt
rgg_save_tool-0.1.1.dist-info/RECORD
