Metadata-Version: 2.3
Name: rgg_save_tool
Version: 0.1.1
Summary: A tool for encrypting and decrypting RGG Studios game saves. (DE Only)
License: MIT
Author: GarnetSunset
Author-email: github@amusement.vision
Requires-Python: >=3.8,<4.0
Classifier: License :: OSI Approved :: MIT License
Classifier: Programming Language :: Python :: 3
Classifier: Programming Language :: Python :: 3.8
Classifier: Programming Language :: Python :: 3.9
Classifier: Programming Language :: Python :: 3.10
Classifier: Programming Language :: Python :: 3.11
Classifier: Programming Language :: Python :: 3.12
Classifier: Programming Language :: Python :: 3.13
Requires-Dist: msgpack (>=1.1.0,<2.0.0)
